lysine/__init__.py
lysine/_identifier.py
lysine/async_utils.py
lysine/bccache.py
lysine/compiler.py
lysine/constants.py
lysine/debug.py
lysine/defaults.py
lysine/environment.py
lysine/exceptions.py
lysine/ext.py
lysine/filters.py
lysine/idtracking.py
lysine/lexer.py
lysine/loaders.py
lysine/meta.py
lysine/nativetypes.py
lysine/nodes.py
lysine/optimizer.py
lysine/parser.py
lysine/py.typed
lysine/runtime.py
lysine/sandbox.py
lysine/tests.py
lysine/utils.py
lysine/visitor.py
lysine-0.1.0.dist-info/LICENSE.txt
lysine-0.1.0.dist-info/METADATA
lysine-0.1.0.dist-info/WHEEL
lysine-0.1.0.dist-info/top_level.txt
lysine-0.1.0.dist-info/RECORD
